docs/docusaurus.config.js
docs/package-lock.json
docs/package.json
docs/sidebars.js
docs/blog/2019-05-28-first-blog-post.md
docs/blog/2019-05-29-long-blog-post.md
docs/blog/2021-08-01-mdx-blog-post.mdx
docs/blog/authors.yml
docs/blog/tags.yml
docs/blog/2021-08-26-welcome/docusaurus-plushie-banner.jpeg
docs/blog/2021-08-26-welcome/index.md
docs/docs/documentation/_category_.json
docs/docs/documentation/manager_files.md
docs/docs/documentation/workflow_results.md
docs/docs/documentation/workflow_steps.md
docs/docs/tutorial/_category_.json
docs/docs/tutorial/add_jobs.md
docs/docs/tutorial/add_result_step.md
docs/docs/tutorial/add_workflow_steps.md
docs/docs/tutorial/add_workflows.md
docs/docs/tutorial/app_setup.md
docs/docs/tutorial/installation.md
docs/docs/tutorial/managers.md
docs/docs/tutorial/tethys_settings.md
docs/docs/tutorial/workflows_page.md
docs/src/components/HomepageFeatures/index.js
docs/src/components/HomepageFeatures/styles.module.css
docs/src/css/custom.css
docs/src/pages/index.js
docs/src/pages/index.module.css
docs/src/pages/markdown-page.md
docs/static/manager_files.zip
docs/static/img/added_workflow_steps_screenshot.png
docs/static/img/condor_scheduler_setup.png
docs/static/img/dark-mode-tethys-icon-with-text.svg
docs/static/img/docusaurus-social-card.jpg
docs/static/img/docusaurus.png
docs/static/img/favicon.ico
docs/static/img/first_spatial_input_step_screenshot.png
docs/static/img/job_running_screenshot.png
docs/static/img/light-mode-tethys-icon-with-text.svg
docs/static/img/logo.svg
docs/static/img/new_workflow_made_screenshot.png
docs/static/img/tethys-icon-only.svg
docs/static/img/undraw_docusaurus_mountain.svg
docs/static/img/undraw_docusaurus_react.svg
docs/static/img/undraw_docusaurus_tree.svg
docs/static/img/workflow_options_select_screenshot.png
docs/static/img/workflow_results_screenshot.png
docs/static/img/workflows-page-final-screenshot.png
docs/static/img/home_page_images/python-icon.svg
tethysext_workflows-1.3.2.dist-info/licenses/LICENSE
tethysext_workflows-1.3.2.dist-info/METADATA
tethysext_workflows-1.3.2.dist-info/WHEEL
tethysext_workflows-1.3.2.dist-info/top_level.txt
tethysext_workflows-1.3.2.dist-info/RECORD
