Metadata-Version: 2.4
Name: tethysext-workflows
Version: 1.3.2
Summary: Tethys extension for adding step-by-step workflows to apps.
Author-email: Jacob Johnson <jjohnson@aquaveo.com>
Classifier: Environment :: Web Environment
Classifier: Framework :: Django
Classifier: Intended Audience :: Developers
Classifier: Operating System :: OS Independent
Classifier: Programming Language :: Python
Classifier: Programming Language :: Python :: 3
Classifier: Programming Language :: Python :: 3.10
Classifier: Topic :: Internet :: WWW/HTTP
Classifier: Topic :: Internet :: WWW/HTTP :: Dynamic Content
License-File: LICENSE
Dynamic: license-file
